async_reduce/__init__.py
async_reduce/async_reduceable.py
async_reduce/async_reducer.py
async_reduce/aux.py
async_reduce/hooks/__init__.py
async_reduce/hooks/base.py
async_reduce/hooks/debug.py
async_reduce/hooks/statistics.py
tests/test_hooks/__init__.py
tests/test_hooks/test_base_multiplehooks.py
tests/test_hooks/test_debug.py
tests/test_hooks/test_statistics_detail.py
tests/test_hooks/test_statistics_overall.py
async_reduce-1.4.dist-info/LICENSE
async_reduce-1.4.dist-info/METADATA
async_reduce-1.4.dist-info/WHEEL
async_reduce-1.4.dist-info/top_level.txt
async_reduce-1.4.dist-info/RECORD
