Metadata-Version: 2.2
Name: async_reduce
Version: 1.4
Summary: Reducer for similar simultaneously coroutines
Home-page: https://github.com/sirkonst/async-reduce
Author: Konstantin Enchant
Author-email: sirkonst@gmail.com
Maintainer: Konstantin Enchant
Maintainer-email: sirkonst@gmail.com
License: MIT
Keywords: asyncio,reduce
Classifier: Development Status :: 5 - Production/Stable
Classifier: License :: OSI Approved :: MIT License
Classifier: Programming Language :: Python :: 3 :: Only
Classifier: Programming Language :: Python :: 3.7
Classifier: Programming Language :: Python :: 3.8
Classifier: Programming Language :: Python :: 3.9
Classifier: Programming Language :: Python :: 3.10
Classifier: Programming Language :: Python :: 3.11
Classifier: Programming Language :: Python :: 3.12
Classifier: Programming Language :: Python :: 3.13
Requires-Python: >=3.7
License-File: LICENSE
Provides-Extra: develop
Requires-Dist: tox~=4.23; extra == "develop"
Requires-Dist: wheel~=0.45; extra == "develop"
Requires-Dist: twine~=6.0; extra == "develop"
Provides-Extra: testing
Requires-Dist: setuptools~=68.2; python_version >= "3.12" and extra == "testing"
Requires-Dist: pytest~=7.2; extra == "testing"
Requires-Dist: pytest-asyncio~=0.20; extra == "testing"
Requires-Dist: coverage~=7.0; extra == "testing"
Requires-Dist: pylama~=8.4; extra == "testing"
Requires-Dist: mypy~=0.991; extra == "testing"
